rfvis/__init__.py
rfvis/__main__.py
rfvis-0.3.1.dist-info/LICENSE
rfvis-0.3.1.dist-info/METADATA
rfvis-0.3.1.dist-info/WHEEL
rfvis-0.3.1.dist-info/entry_points.txt
rfvis-0.3.1.dist-info/top_level.txt
rfvis-0.3.1.dist-info/RECORD
