Metadata-Version: 2.1
Name: rfvis
Version: 0.3.1
Summary: A tool for visualizing the structure and performance of Random Forests
Home-page: https://github.com/birnbaum/rfvis
Author: Philipp Wiesner
Author-email: mail@philippwiesner.com
License: MIT
Project-URL: Bug Tracker, https://github.com/birnbaum/rfvis/issues
Keywords: random-forest,visualization,decision-trees,d3js,react
Platform: UNKNOWN
Classifier: Development Status :: 4 - Beta
Classifier: Environment :: Console
Classifier: Environment :: Web Environment
Classifier: Intended Audience :: Education
Classifier: Intended Audience :: Science/Research
Classifier: License :: OSI Approved :: MIT License
Classifier: Operating System :: OS Independent
Classifier: Programming Language :: JavaScript
Classifier: Programming Language :: Python
Classifier: Programming Language :: Python :: 2
Classifier: Programming Language :: Python :: 2.7
Classifier: Programming Language :: Python :: 3
Classifier: Programming Language :: Python :: 3.4
Classifier: Programming Language :: Python :: 3.5
Classifier: Programming Language :: Python :: 3.6
Classifier: Programming Language :: Python :: 3.7
Classifier: Topic :: Education
Classifier: Topic :: Scientific/Engineering :: Visualization
Requires-Dist: click
Requires-Dist: flask
